deckflow/__init__.py
deckflow/deck.py
deckflow/slide.py
deckflow/adders/__init__.py
deckflow/adders/image_adder.py
deckflow/content/__init__.py
deckflow/content/chart_extractor.py
deckflow/content/duplicate.py
deckflow/content/element_remover.py
deckflow/content/finder.py
deckflow/content/registry.py
deckflow/content/table_extractor.py
deckflow/content/text_extractor.py
deckflow/elements/__init__.py
deckflow/elements/chart.py
deckflow/elements/table.py
deckflow/elements/text.py
deckflow/formatters/__init__.py
deckflow/formatters/color_analyzer.py
deckflow/formatters/font_properties.py
deckflow/formatters/slide_printer.py
deckflow/formatters/table_printer.py
deckflow/updaters/__init__.py
deckflow/updaters/chart_updater.py
deckflow/updaters/table_updater.py
deckflow/updaters/text_updater.py
deckflow-0.1.4.dist-info/licenses/LICENSE
deckflow-0.1.4.dist-info/METADATA
deckflow-0.1.4.dist-info/WHEEL
deckflow-0.1.4.dist-info/top_level.txt
deckflow-0.1.4.dist-info/RECORD
