Metadata-Version: 2.4
Name: deckflow
Version: 0.1.4
Summary: Programmatic PowerPoint manager
Author: Nicolas Pogeant
License-Expression: MIT
Project-URL: Homepage, https://github.com/npogeant/deckflow
Requires-Python: >=3.9
License-File: LICENSE
Requires-Dist: python-pptx>=1.0.2
Provides-Extra: test
Requires-Dist: pytest>=7.0.0; extra == "test"
Dynamic: license-file
